pygeohydro/__init__.py
pygeohydro/exceptions.py
pygeohydro/helpers.py
pygeohydro/levee.py
pygeohydro/nfhl.py
pygeohydro/nid.py
pygeohydro/nlcd.py
pygeohydro/nwis.py
pygeohydro/plot.py
pygeohydro/print_versions.py
pygeohydro/py.typed
pygeohydro/pygeohydro.py
pygeohydro/stnfloodevents.py
pygeohydro/us_abbrs.py
pygeohydro/waterdata.py
pygeohydro/watershed.py
pygeohydro-0.19.4.dist-info/METADATA
pygeohydro-0.19.4.dist-info/WHEEL
pygeohydro-0.19.4.dist-info/licenses/AUTHORS.rst
pygeohydro-0.19.4.dist-info/licenses/LICENSE
pygeohydro-0.19.4.dist-info/RECORD
