Metadata-Version: 2.4
Name: pygeohydro
Version: 0.19.4
Summary: Access geospatial web services that offer hydrological data
Project-URL: Changelog, https://docs.hyriver.io/changelogs/pygeohydro.html
Project-URL: CI, https://github.com/hyriver/pygeohydro/actions
Project-URL: Homepage, https://docs.hyriver.io/readme/pygeohydro.html
Project-URL: Issues, https://github.com/hyriver/pygeohydro/issues
Author-email: Taher Chegini <cheginit@gmail.com>
License: MIT
License-File: AUTHORS.rst
License-File: LICENSE
Classifier: Development Status :: 4 - Beta
Classifier: Intended Audience :: Science/Research
Classifier: License :: OSI Approved :: MIT License
Classifier: Operating System :: OS Independent
Classifier: Programming Language :: Python
Classifier: Programming Language :: Python :: 3 :: Only
Classifier: Programming Language :: Python :: 3.9
Classifier: Programming Language :: Python :: 3.10
Classifier: Programming Language :: Python :: 3.11
Classifier: Programming Language :: Python :: 3.12
Classifier: Programming Language :: Python :: 3.13
Classifier: Topic :: Scientific/Engineering
Classifier: Topic :: Scientific/Engineering :: GIS
Classifier: Topic :: Scientific/Engineering :: Hydrology
Classifier: Typing :: Typed
Requires-Python: >=3.9
Requires-Dist: async-retriever<0.20,>=0.19.3
Requires-Dist: cytoolz
Requires-Dist: defusedxml
Requires-Dist: geopandas>=1
Requires-Dist: h5netcdf
Requires-Dist: hydrosignatures<0.20,>=0.19.3
Requires-Dist: numpy>=2
Requires-Dist: pandas>=1
Requires-Dist: pygeoogc<0.20,>=0.19.4
Requires-Dist: pygeoutils<0.20,>=0.19.5
Requires-Dist: pynhd<0.20,>=0.19.3
Requires-Dist: pyproj>=3.0.1
Requires-Dist: rioxarray>=0.15
Requires-Dist: scipy
Requires-Dist: shapely>=2
Requires-Dist: xarray>=2024.7
Provides-Extra: plot
Requires-Dist: folium; extra == 'plot'
Requires-Dist: matplotlib>=3.5; extra == 'plot'
Provides-Extra: stac
Requires-Dist: planetary-computer; extra == 'stac'
Requires-Dist: pystac-client; extra == 'stac'
Provides-Extra: test
Requires-Dist: pytest-cov; extra == 'test'
Requires-Dist: pytest-sugar; extra == 'test'
